{"request_id":"9686478262c58e29d1e0247d4a95dca4","results":{"ticker":"MELI","name":"Mercado Libre, Inc","market":"stocks","locale":"us","primary_exchange":"XNAS","type":"CS","active":true,"currency_name":"usd","cik":"0001099590","composite_figi":"BBG000GQPB11","share_class_figi":"BBG001SM32G3","market_cap":69685704251.73,"phone_number":"598-2-2927-2770","address":{"address1":"DR. LUIS BONAVITA 1294 OF. 1733 TOWER II","city":"MONTEVIDEO","state":"X3","postal_code":"11300"},"description":"MercadoLibre runs the largest e-commerce marketplace in Latin America, connecting a network of more than 148 million active users and 1 million active sellers as of the end of 2022 across an 18-country footprint. The company also operates a host of complementary businesses, with shipping solutions (Mercado Envios), a payment and financing operation (Mercado Pago and Mercado Credito), advertisements (Mercado Clics), classifieds, and a turnkey e-commerce solution (Mercado Shops) rounding out its arsenal. MercadoLibre generates revenue from final value fees, advertising royalties, payment processing, insertion fees, subscription fees, and interest income from consumer and small-business lending.","sic_code":"7389","sic_description":"SERVICES-BUSINESS SERVICES, NEC","ticker_root":"MELI","homepage_url":"https://www.mercadolibre.com","total_employees":40548,"list_date":"2007-08-10","branding":{"logo_url":"https://api.polygon.io/v1/reference/company-branding/bWVyY2Fkb2xpYnJlLmNvbQ/images/2023-11-01_logo.svg","icon_url":"https://api.polygon.io/v1/reference/company-branding/bWVyY2Fkb2xpYnJlLmNvbQ/images/2023-11-01_icon.jpeg"},"share_class_shares_outstanding":50560000,"weighted_shares_outstanding":50559537,"round_lot":100},"status":"OK"}
