{"request_id":"0534470dec43e3a299e28f023b1e62af","results":{"ticker":"MU","name":"MICRON TECHNOLOGY INC","market":"stocks","locale":"us","primary_exchange":"XNAS","active":true,"currency_name":"usd","cik":"0000798287","composite_figi":"BBG000C5Z1S3","share_class_figi":"BBG001S6P675","market_cap":73111539184.5,"phone_number":"(479) 361-9111","address":{"address1":"297 WEST HENRI DE TONTI BLVD","city":"TONTITOWN","state":"AR","postal_code":"72770"},"sic_code":"4213","sic_description":"TRUCKING (NO LOCAL)","ticker_root":"MU","list_date":"1989-05-16","weighted_shares_outstanding":1037043109,"round_lot":100},"status":"OK"}
