{"request_id":"bd891d854e4220689ce65b7cea94a9dc","results":{"ticker":"CMCSA","name":"Comcast Corp","market":"stocks","locale":"us","primary_exchange":"XNAS","type":"CS","active":true,"currency_name":"usd","cik":"0001166691","composite_figi":"BBG000BFT2L4","share_class_figi":"BBG001S5PXL2","market_cap":171709902092.34,"phone_number":"215-286-1700","address":{"address1":"ONE COMCAST CENTER","city":"PHILADELPHIA","state":"PA","postal_code":"19103-2838"},"description":"Comcast is made up of three parts. The core cable business owns networks capable of providing television, internet access, and phone services to 62 million U.S. homes and businesses, or nearly half of the country. About 55% of the homes in this territory subscribe to at least one Comcast service. Comcast acquired NBCUniversal from General Electric in 2011. NBCU owns several cable networks, including CNBC, MSNBC, and USA, the NBC broadcast network, the Peacock streaming platform, several local NBC affiliates, Universal Studios, and several theme parks. Sky, acquired in 2018, is the dominant television provider in the U.K. and has invested heavily in proprietary content to build this position. Sky is also the largest pay-television provider in Italy and has a presence in Germany and Austria.","sic_code":"4841","sic_description":"CABLE & OTHER PAY TELEVISION SERVICES","ticker_root":"CMCS","ticker_suffix":"A","homepage_url":"https://www.comcastcorporation.com","total_employees":186000,"list_date":"1988-07-07","share_class_shares_outstanding":4015640000,"weighted_shares_outstanding":4025079749,"round_lot":100},"status":"OK"}
