{"results":[{"cash_amount":0.5,"currency":"USD","declaration_date":"2024-02-01","dividend_type":"CD","ex_dividend_date":"2024-02-21","frequency":4,"id":"Ef8795a4515fee5e57f05030294218f0aac8514e8f060886876b30f6d92337cd1","pay_date":"2024-03-26","record_date":"2024-02-22","ticker":"META"},{"cash_amount":0.5,"currency":"USD","declaration_date":"2024-05-30","dividend_type":"CD","ex_dividend_date":"2024-06-14","frequency":4,"id":"Edbd30f584bd978a9c21fa5a5f829a94f2c66b401057211d3bbf2f8b2963750b8","pay_date":"2024-06-26","record_date":"2024-06-14","ticker":"META"},{"cash_amount":0.5,"currency":"USD","declaration_date":"2024-09-05","dividend_type":"CD","ex_dividend_date":"2024-09-16","frequency":4,"id":"Ebb8825e317cd430d0ff8210f0b8cd537870a77a983de9d499bf86ed2a7b14c4e","pay_date":"2024-09-26","record_date":"2024-09-16","ticker":"META"},{"cash_amount":0.5,"currency":"USD","declaration_date":"2024-12-05","dividend_type":"CD","ex_dividend_date":"2024-12-16","frequency":4,"id":"Ecec59fc797c01fe342c9693ce95f194450e2ca76f632da986c5e24e4836c64cf","pay_date":"2024-12-27","record_date":"2024-12-16","ticker":"META"},{"cash_amount":0.525,"currency":"USD","declaration_date":"2025-02-13","dividend_type":"CD","ex_dividend_date":"2025-03-14","frequency":4,"id":"E27c60f82e95faa5cf7f8c34f621350af97b3081412a630dfba702f9679f7ec36","pay_date":"2025-03-26","record_date":"2025-03-14","ticker":"META"}],"status":"OK","request_id":"4b63cc94e9b25fa3cc66f10b02c44745"}
